README.rst
setup.py
repyt/__init__.py
repyt/repyt.py
repyt.egg-info/PKG-INFO
repyt.egg-info/SOURCES.txt
repyt.egg-info/dependency_links.txt
repyt.egg-info/entry_points.txt
repyt.egg-info/not-zip-safe
repyt.egg-info/requires.txt
repyt.egg-info/top_level.txt